LICENSE
README.md
setup.py
alpha_analysis/__init__.py
alpha_analysis.egg-info/PKG-INFO
alpha_analysis.egg-info/SOURCES.txt
alpha_analysis.egg-info/dependency_links.txt
alpha_analysis.egg-info/requires.txt
alpha_analysis.egg-info/top_level.txt
alpha_analysis/generative_models/__init__.py
alpha_analysis/generative_models/gan.py
alpha_analysis/generative_models/vae.py
alpha_analysis/modeling_financial_processes/__init__.py
alpha_analysis/modeling_financial_processes/gbm.py
alpha_analysis/modeling_financial_processes/heston.py
alpha_analysis/modeling_financial_processes/jump_diffusion.py
alpha_analysis/modeling_financial_processes/multi_asset_models.py
alpha_analysis/modeling_financial_processes/ou_process.py
alpha_analysis/models/__init__.py
alpha_analysis/models/ml_models.py
alpha_analysis/portfolio/__init__.py
alpha_analysis/portfolio/clustering.py
alpha_analysis/portfolio/optimization.py
alpha_analysis/portfolio/performance.py
alpha_analysis/portfolio/portfolio_features.py
alpha_analysis/signal_generation/__init__.py
alpha_analysis/signal_generation/fundamental_signals.py
alpha_analysis/signal_generation/sentiment_analysis.py
alpha_analysis/signal_generation/technical_signals.py
alpha_analysis/time_series/__init__.py
alpha_analysis/time_series/arima.py
alpha_analysis/time_series/feature_selection.py
alpha_analysis/time_series/garch.py
alpha_analysis/time_series/state_space_models.py
alpha_analysis/time_series/var.py
alpha_analysis/trading/__init__.py
alpha_analysis/trading/backtesting.py
alpha_analysis/trading/risk_management.py