Metadata-Version: 2.1
Name: alpha-analysis
Version: 1.2.2
Summary: Library for analyzing financial data_preprocessing using ML and classical approaches
Home-page: https://github.com/ImplicitLayer/AlphaAnalysis
Author: ArtemBurenok
Author-email: burenok023@gmail.com
License: Apache License, version 2.0
Classifier: Programming Language :: Python :: 3
Requires-Python: >=3.10
License-File: LICENSE
